{
  "system": "gba",
  "normalized_title": "kirbyamazingmirror",
  "display_name": "Kirby _ the Amazing Mirror (USA, Europe) (Code Breaker)",
  "aliases": [],
  "sources": {
    "libretro_database": {
      "path": "libretro_database\\cht\\Nintendo - Game Boy Advance\\Kirby _ the Amazing Mirror (USA, Europe) (Code Breaker).cht",
      "total_cheat_rows": 13,
      "raw_entry_count": 13,
      "distinct_address_count": 13,
      "sample_raw_entries": [
        {
          "code": "32020FE0",
          "desc": "Infinite Health",
          "address": "0x02020FE0"
        },
        {
          "code": "32020FE2",
          "desc": "Infinite Lives",
          "address": "0x02020FE2"
        },
        {
          "code": "32020FBC",
          "desc": "Infinite Whistle",
          "address": "0x02020FBC"
        },
        {
          "code": "32020FE3",
          "desc": "Kirby State Modifier",
          "address": "0x02020FE3"
        },
        {
          "code": "42028CA0",
          "desc": "All Levels/Doors Accessed",
          "address": "0x02028CA0"
        },
        {
          "code": "42028C10",
          "desc": "Open All Connections",
          "address": "0x02028C10"
        },
        {
          "code": "32038970",
          "desc": "Have All Mirror Pieces",
          "address": "0x02038970"
        },
        {
          "code": "82038974",
          "desc": "Have All Spray Paint In Collection",
          "address": "0x02038974"
        },
        {
          "code": "82038978",
          "desc": "Have Sound Player And All Music/Sounds In Collection",
          "address": "0x02038978"
        },
        {
          "code": "8203897C",
          "desc": "Have All Maps In Collection",
          "address": "0x0203897C"
        },
        {
          "code": "32038980",
          "desc": "Have All Vitality Upgrades In Collection",
          "address": "0x02038980"
        },
        {
          "code": "42038960",
          "desc": "Have All Chests/Switches Opened",
          "address": "0x02038960"
        },
        {
          "code": "3203896A",
          "desc": "Have All Chests/Switches Opened",
          "address": "0x0203896A"
        }
      ]
    },
    "bobwin": {
      "path": "bobwin\\gba\\Kirby _ the Amazing Mirror (USA, Europe) (Code Breaker).cht",
      "total_cheat_rows": 13,
      "raw_entry_count": 13,
      "distinct_address_count": 13,
      "sample_raw_entries": [
        {
          "code": "32020FE0",
          "desc": "Infinite Health",
          "address": "0x02020FE0"
        },
        {
          "code": "32020FE2",
          "desc": "Infinite Lives",
          "address": "0x02020FE2"
        },
        {
          "code": "32020FBC",
          "desc": "Infinite Whistle",
          "address": "0x02020FBC"
        },
        {
          "code": "32020FE3",
          "desc": "Kirby State Modifier",
          "address": "0x02020FE3"
        },
        {
          "code": "42028CA0",
          "desc": "All Levels/Doors Accessed",
          "address": "0x02028CA0"
        },
        {
          "code": "42028C10",
          "desc": "Open All Connections",
          "address": "0x02028C10"
        },
        {
          "code": "32038970",
          "desc": "Have All Mirror Pieces",
          "address": "0x02038970"
        },
        {
          "code": "82038974",
          "desc": "Have All Spray Paint In Collection",
          "address": "0x02038974"
        },
        {
          "code": "82038978",
          "desc": "Have Sound Player And All Music/Sounds In Collection",
          "address": "0x02038978"
        },
        {
          "code": "8203897C",
          "desc": "Have All Maps In Collection",
          "address": "0x0203897C"
        },
        {
          "code": "32038980",
          "desc": "Have All Vitality Upgrades In Collection",
          "address": "0x02038980"
        },
        {
          "code": "42038960",
          "desc": "Have All Chests/Switches Opened",
          "address": "0x02038960"
        },
        {
          "code": "3203896A",
          "desc": "Have All Chests/Switches Opened",
          "address": "0x0203896A"
        }
      ]
    }
  },
  "recommended_primary_source": "libretro_database",
  "notes": [
    "Only cheat-address style raw entries available."
  ]
}
