{
  "schema": "qrd.rumble.snes.v1",
  "game": {
    "name": "Killer Instinct (USA)",
    "system": "snes"
  },
  "source": {
    "cht_file": "E:\\bob\\retro\\BOBwin_Abril_2024.7z\\cheats\\retroarch\\Snes9x\\Killer Instinct (USA).cht",
    "parser": "retroarch_kv"
  },
  "triggers": [],
  "unsupported_evidence": [
    {
      "code": "3C61-D4DF",
      "desc": "Master Code - Must Be Entered",
      "kind": "game_genie"
    },
    {
      "code": "CBEC-37AF",
      "desc": "Play As Eyedol",
      "kind": "game_genie"
    },
    {
      "code": "6DE8-3D0F",
      "desc": "Play As Eyedol",
      "kind": "game_genie"
    },
    {
      "code": "6D64-44D5",
      "desc": "Play As Eyedol",
      "kind": "game_genie"
    },
    {
      "code": "CB64-4D61",
      "desc": "Start A Game And Watch The Ending (Use `Practice Mode' To Select Different Characters)",
      "kind": "game_genie"
    },
    {
      "code": "CCE8-47D2",
      "desc": "Win After 1 Victory",
      "kind": "game_genie"
    },
    {
      "code": "C8E8-47D2",
      "desc": "Win After 2 Victories",
      "kind": "game_genie"
    },
    {
      "code": "CAE8-47D2",
      "desc": "Win After 3 Victories",
      "kind": "game_genie"
    },
    {
      "code": "C2E8-47D2",
      "desc": "Win After 4 Victories",
      "kind": "game_genie"
    },
    {
      "code": "C3E8-47D2",
      "desc": "Win After 5 Victories",
      "kind": "game_genie"
    },
    {
      "code": "EEC1-34AF",
      "desc": "Player 1 Takes All Damage",
      "kind": "game_genie"
    },
    {
      "code": "1D1B-1DA7",
      "desc": "Players Can Pass Through Each Other",
      "kind": "game_genie"
    },
    {
      "code": "C265-1467",
      "desc": "Always Fight Jago",
      "kind": "game_genie"
    },
    {
      "code": "60E6-47D2",
      "desc": "Always Fight Jago",
      "kind": "game_genie"
    },
    {
      "code": "C265-1467",
      "desc": "Always Fight Combo",
      "kind": "game_genie"
    },
    {
      "code": "6EE6-47D2",
      "desc": "Always Fight Combo",
      "kind": "game_genie"
    },
    {
      "code": "C265-1467",
      "desc": "Always Fight Thunder",
      "kind": "game_genie"
    },
    {
      "code": "6BE6-47D2",
      "desc": "Always Fight Thunder",
      "kind": "game_genie"
    },
    {
      "code": "C265-1467",
      "desc": "Always Fight Glacius",
      "kind": "game_genie"
    },
    {
      "code": "6FE6-47D2",
      "desc": "Always Fight Glacius",
      "kind": "game_genie"
    },
    {
      "code": "C265-1467",
      "desc": "Always Fight Cinder",
      "kind": "game_genie"
    },
    {
      "code": "6DE6-47D2",
      "desc": "Always Fight Cinder",
      "kind": "game_genie"
    },
    {
      "code": "C265-1467",
      "desc": "Always Fight Orchid",
      "kind": "game_genie"
    },
    {
      "code": "64E6-47D2",
      "desc": "Always Fight Orchid",
      "kind": "game_genie"
    },
    {
      "code": "C265-1467",
      "desc": "Always Fight Riptor",
      "kind": "game_genie"
    },
    {
      "code": "BOE6-47D2",
      "desc": "Always Fight Riptor",
      "kind": "unsupported"
    },
    {
      "code": "C265-1467",
      "desc": "Always Fight Sabrewulf",
      "kind": "game_genie"
    },
    {
      "code": "CBE6-4702",
      "desc": "Always Fight Sabrewulf",
      "kind": "game_genie"
    },
    {
      "code": "C265-1467",
      "desc": "Always Fight Spinal",
      "kind": "game_genie"
    },
    {
      "code": "CBEC-4702",
      "desc": "Always Fight Spinal",
      "kind": "game_genie"
    },
    {
      "code": "C265-1467",
      "desc": "Always Fight Fulgore",
      "kind": "game_genie"
    },
    {
      "code": "CBE8-4D62",
      "desc": "Always Fight Fulgore",
      "kind": "game_genie"
    },
    {
      "code": "C265-1467",
      "desc": "Always Fight Eyedol",
      "kind": "game_genie"
    },
    {
      "code": "CBE8-4FA2",
      "desc": "Always Fight Eyedol",
      "kind": "game_genie"
    },
    {
      "code": "6D64-44D5",
      "desc": "Stay As Eyedol Once You Unlock Him Until You Lose And Choose Someone Else",
      "kind": "game_genie"
    }
  ]
}
