{
  "system": "pce",
  "normalized_title": "knightriderspecial",
  "display_name": "Knight Rider Special (Japan)",
  "aliases": [],
  "sources": {
    "libretro_database": {
      "path": "libretro_database\\cht\\NEC - PC Engine - TurboGrafx 16\\Knight Rider Special (Japan).cht",
      "total_cheat_rows": 2,
      "raw_entry_count": 2,
      "distinct_address_count": 2,
      "sample_raw_entries": [
        {
          "code": "1f0086:89",
          "desc": "Infinite Time",
          "address": "0x1F0086"
        },
        {
          "code": "1f0088:16",
          "desc": "Infinite Energy",
          "address": "0x1F0088"
        }
      ]
    }
  },
  "recommended_primary_source": "libretro_database",
  "notes": [
    "Only cheat-address style raw entries available."
  ]
}
