{
  "system": "snes",
  "normalized_title": "dragonview",
  "display_name": "Dragon View (USA) (Action Replay)",
  "aliases": [
    "Dragon View (USA) (Action Replay)",
    "Dragon View (USA) (Game Genie)",
    "Dragon View (USA)"
  ],
  "sources": {
    "libretro_database": {
      "path": "libretro_database\\cht\\Nintendo - Super Nintendo Entertainment System\\Dragon View (USA).cht",
      "total_cheat_rows": 45,
      "raw_entry_count": 46,
      "distinct_address_count": 42,
      "sample_raw_entries": [
        {
          "code": "7E7095E7",
          "desc": "Max Experience",
          "address": "0x7E7095"
        },
        {
          "code": "7E709603",
          "desc": "Max Experience",
          "address": "0x7E7096"
        },
        {
          "code": "7E21310F",
          "desc": "Max Money [Jade]",
          "address": "0x7E2131"
        },
        {
          "code": "7E213227",
          "desc": "Max Money [Jade]",
          "address": "0x7E2132"
        },
        {
          "code": "7E98E9FF",
          "desc": "Max Attack Power",
          "address": "0x7E98E9"
        },
        {
          "code": "7E98EAFF",
          "desc": "Max Defence Power",
          "address": "0x7E98EA"
        },
        {
          "code": "7E6FCAB8",
          "desc": "Infinite HP",
          "address": "0x7E6FCA"
        },
        {
          "code": "7E6FCBBE",
          "desc": "Max HP",
          "address": "0x7E6FCB"
        },
        {
          "code": "7E6FCBBE",
          "desc": "Max HP",
          "address": "0x7E6FCB"
        },
        {
          "code": "7E21310F",
          "desc": "Max Money (Jade)",
          "address": "0x7E2131"
        },
        {
          "code": "7E213227",
          "desc": "Max Money (Jade)",
          "address": "0x7E2132"
        },
        {
          "code": "7E6FCBBE",
          "desc": "Max HP",
          "address": "0x7E6FCB"
        },
        {
          "code": "7E200101",
          "desc": "Have Dynamite",
          "address": "0x7E2001"
        },
        {
          "code": "7E210201",
          "desc": "Have Dynamite",
          "address": "0x7E2102"
        },
        {
          "code": "7E210401",
          "desc": "Have 30 Arrows",
          "address": "0x7E2104"
        },
        {
          "code": "7E21051E",
          "desc": "Have 30 Arrows",
          "address": "0x7E2105"
        },
        {
          "code": "7E210601",
          "desc": "Have 3 Crystals",
          "address": "0x7E2106"
        },
        {
          "code": "7E210703",
          "desc": "Have 3 Crystals",
          "address": "0x7E2107"
        },
        {
          "code": "7E210801",
          "desc": "Have 3 Potions",
          "address": "0x7E2108"
        },
        {
          "code": "7E210903",
          "desc": "Have 3 Potions",
          "address": "0x7E2109"
        },
        {
          "code": "7E210A00",
          "desc": "Have Fire Ring / Level Modifier 1, 2, 3...",
          "address": "0x7E210A"
        },
        {
          "code": "7E210C00",
          "desc": "Have Ice Ring / Level Modifier 1, 2, 3...",
          "address": "0x7E210C"
        },
        {
          "code": "7E210E00",
          "desc": "Have Lightning Ring / Level Modifier 1, 2, 3...",
          "address": "0x7E210E"
        },
        {
          "code": "7E211001",
          "desc": "Have 99 Fruit",
          "address": "0x7E2110"
        },
        {
          "code": "7E211163",
          "desc": "Have 99 Fruit",
          "address": "0x7E2111"
        }
      ]
    }
  },
  "recommended_primary_source": "libretro_database",
  "notes": [
    "Only cheat-address style raw entries available."
  ]
}
