{
  "system": "snes",
  "normalized_title": "talesofphantasia",
  "display_name": "Tales of Phantasia (Japan) (Action Replay)",
  "aliases": [
    "Tales of Phantasia (Japan) (Game Genie)",
    "Tales of Phantasia (Japan)"
  ],
  "sources": {
    "libretro_database": {
      "path": "libretro_database\\cht\\Nintendo - Super Nintendo Entertainment System\\Tales of Phantasia (Japan).cht",
      "total_cheat_rows": 866,
      "raw_entry_count": 956,
      "distinct_address_count": 848,
      "sample_raw_entries": [
        {
          "code": "7E21A100",
          "desc": "Room modifier",
          "address": "0x7E21A1"
        },
        {
          "code": "7E14B37F",
          "desc": "Have 9999999 Gold",
          "address": "0x7E14B3"
        },
        {
          "code": "7E14B496",
          "desc": "Have 9999999 Gold",
          "address": "0x7E14B4"
        },
        {
          "code": "7E14B598",
          "desc": "Have 9999999 Gold",
          "address": "0x7E14B5"
        },
        {
          "code": "7E1484FF",
          "desc": "Always Have Maximum Food",
          "address": "0x7E1484"
        },
        {
          "code": "7E14857F",
          "desc": "Always Have Maximum Food",
          "address": "0x7E1485"
        },
        {
          "code": "7E1486FF",
          "desc": "Always Have Maximum Food",
          "address": "0x7E1486"
        },
        {
          "code": "7E14877F",
          "desc": "Always Have Maximum Food",
          "address": "0x7E1487"
        },
        {
          "code": "7E1593FF",
          "desc": "Always Have All Special Items",
          "address": "0x7E1593"
        },
        {
          "code": "7E1594FF",
          "desc": "Always Have All Special Items",
          "address": "0x7E1594"
        },
        {
          "code": "7E1595FF",
          "desc": "Always Have All Special Items",
          "address": "0x7E1595"
        },
        {
          "code": "7E14A500",
          "desc": "Time Period Modifier",
          "address": "0x7E14A5"
        },
        {
          "code": "7E709401",
          "desc": "Have Wagasumi",
          "address": "0x7E7094"
        },
        {
          "code": "7E709181",
          "desc": "Have Tiger Teeth &amp; Learned at 100%",
          "address": "0x7E7091"
        },
        {
          "code": "7E715664",
          "desc": "Have Tiger Teeth &amp; Learned at 100%",
          "address": "0x7E7156"
        },
        {
          "code": "7E709301",
          "desc": "Have Gale Shield",
          "address": "0x7E7093"
        },
        {
          "code": "7E709281",
          "desc": "Have Psion Bolt &amp; Learned at 100%",
          "address": "0x7E7092"
        },
        {
          "code": "7E715764",
          "desc": "Have Psion Bolt &amp; Learned at 100%",
          "address": "0x7E7157"
        },
        {
          "code": "7E70B581",
          "desc": "Have Soul Strike",
          "address": "0x7E70B5"
        },
        {
          "code": "7E70B381",
          "desc": "Have Cinder Hawk",
          "address": "0x7E70B3"
        },
        {
          "code": "7E70B281",
          "desc": "Have Burning Soul",
          "address": "0x7E70B2"
        },
        {
          "code": "7E70B181",
          "desc": "Have Odin's Wrath",
          "address": "0x7E70B1"
        },
        {
          "code": "7E70AE81",
          "desc": "Have Tempest",
          "address": "0x7E70AE"
        },
        {
          "code": "7E70AD81",
          "desc": "Have Thor's Wrath",
          "address": "0x7E70AD"
        },
        {
          "code": "7E70AC81",
          "desc": "Have Bolt Crash",
          "address": "0x7E70AC"
        }
      ]
    }
  },
  "recommended_primary_source": "libretro_database",
  "notes": [
    "Only cheat-address style raw entries available."
  ]
}
