{
  "system": "genesis",
  "normalized_title": "nekketsukoukoudodgeballbusoccerhenmd",
  "display_name": "Nekketsu Koukou Dodgeball-bu - Soccer Hen MD (Japan)",
  "aliases": [],
  "sources": {
    "libretro_database": {
      "path": "libretro_database\\cht\\Sega - Mega Drive - Genesis\\Nekketsu Koukou Dodgeball-bu - Soccer Hen MD (Japan).cht",
      "total_cheat_rows": 2,
      "raw_entry_count": 1,
      "distinct_address_count": 1,
      "sample_raw_entries": [
        {
          "code": "FFF8D2:0000",
          "desc": "Cpu Score Always In Zero",
          "address": "0xFFF8D2"
        }
      ]
    }
  },
  "recommended_primary_source": "libretro_database",
  "notes": [
    "Only cheat-address style raw entries available."
  ]
}
