{
  "system": "genesis",
  "normalized_title": "spaceinvaders90",
  "display_name": "Space Invaders 90 (Japan) (Action Replay)",
  "aliases": [
    "Space Invaders 90 (Japan)"
  ],
  "sources": {
    "libretro_database": {
      "path": "libretro_database\\cht\\Sega - Mega Drive - Genesis\\Space Invaders 90 (Japan).cht",
      "total_cheat_rows": 11,
      "raw_entry_count": 3,
      "distinct_address_count": 3,
      "sample_raw_entries": [
        {
          "code": "FF05C2:0009",
          "desc": "Infinite Lives",
          "address": "0xFF05C2"
        },
        {
          "code": "FF05C4:0009",
          "desc": "Infinite Shields",
          "address": "0xFF05C4"
        },
        {
          "code": "FF04CA:0009",
          "desc": "Infinite Credits (Continues)",
          "address": "0xFF04CA"
        }
      ]
    }
  },
  "recommended_primary_source": "libretro_database",
  "notes": [
    "Only cheat-address style raw entries available."
  ]
}
