{
  "system": "genesis",
  "normalized_title": "ultimateqix",
  "display_name": "Ultimate QIX (USA)",
  "aliases": [],
  "sources": {
    "libretro_database": {
      "path": "libretro_database\\cht\\Sega - Mega Drive - Genesis\\Ultimate QIX (USA).cht",
      "total_cheat_rows": 40,
      "raw_entry_count": 5,
      "distinct_address_count": 4,
      "sample_raw_entries": [
        {
          "code": "FFB582:0071",
          "desc": "Infinite Time (Micro-Seconds)",
          "address": "0xFFB582"
        },
        {
          "code": "FFB582:0071",
          "desc": "Infinite Time (Seconds)",
          "address": "0xFFB582"
        },
        {
          "code": "FFB584:0071",
          "desc": "Infinite Time (Minutes)",
          "address": "0xFFB584"
        },
        {
          "code": "FFB58C:0009",
          "desc": "Infinite Lives",
          "address": "0xFFB58C"
        },
        {
          "code": "FFB58E:0000",
          "desc": "Invincibility",
          "address": "0xFFB58E"
        }
      ]
    }
  },
  "recommended_primary_source": "libretro_database",
  "notes": [
    "Only cheat-address style raw entries available."
  ]
}
