{
  "system": "nes",
  "normalized_title": "lostwordofjennyushinawaretamessage",
  "display_name": "Lost Word of Jenny - Ushinawareta Message (Japan)",
  "aliases": [],
  "sources": {
    "libretro_database": {
      "path": "libretro_database\\cht\\Nintendo - Nintendo Entertainment System\\Lost Word of Jenny - Ushinawareta Message (Japan).cht",
      "total_cheat_rows": 9,
      "raw_entry_count": 11,
      "distinct_address_count": 11,
      "sample_raw_entries": [
        {
          "code": "022F:10",
          "desc": "Infinite Health",
          "address": "0x022F"
        },
        {
          "code": "0239:09",
          "desc": "Infinite Lives",
          "address": "0x0239"
        },
        {
          "code": "04AD:09",
          "desc": "Max Score P1",
          "address": "0x04AD"
        },
        {
          "code": "04AE:09",
          "desc": "Max Score P1",
          "address": "0x04AE"
        },
        {
          "code": "04AF:09",
          "desc": "Max Score P1",
          "address": "0x04AF"
        },
        {
          "code": "04B0:09",
          "desc": "Max Score P1",
          "address": "0x04B0"
        },
        {
          "code": "04B1:09",
          "desc": "Max Score P1",
          "address": "0x04B1"
        },
        {
          "code": "04B2:09",
          "desc": "Max Score P1",
          "address": "0x04B2"
        },
        {
          "code": "04B3:09",
          "desc": "Max Score P1",
          "address": "0x04B3"
        },
        {
          "code": "0240:D6",
          "desc": "Invincible",
          "address": "0x0240"
        },
        {
          "code": "06D7:01",
          "desc": "Hyper Speed Music",
          "address": "0x06D7"
        }
      ]
    }
  },
  "recommended_primary_source": "libretro_database",
  "notes": [
    "Only cheat-address style raw entries available."
  ]
}
