{
  "system": "gbc",
  "normalized_title": "ganbaregoemonmononokedouchuutobidasenabebugyou",
  "display_name": "Ganbare Goemon - Mononoke Douchuu Tobidase Nabebugyou! (Japan) (SGB Enhanced) (GB Compatible)",
  "aliases": [],
  "sources": {
    "libretro_database": {
      "path": "libretro_database\\cht\\Nintendo - Game Boy Color\\Ganbare Goemon - Mononoke Douchuu Tobidase Nabebugyou! (Japan) (SGB Enhanced) (GB Compatible).cht",
      "total_cheat_rows": 1,
      "raw_entry_count": 0,
      "distinct_address_count": 0,
      "sample_raw_entries": []
    }
  },
  "recommended_primary_source": null,
  "notes": []
}
