{
  "system": "gb",
  "normalized_title": "humans",
  "display_name": "Humans, The (USA, Europe) (Game Genie)",
  "aliases": [
    "Humans, The (USA, Europe) (Game Genie)"
  ],
  "sources": {
    "libretro_database": {
      "path": "libretro_database\\cht\\Nintendo - Game Boy\\Humans, The (USA, Europe) (Game Genie).cht",
      "total_cheat_rows": 5,
      "raw_entry_count": 0,
      "distinct_address_count": 0,
      "sample_raw_entries": []
    }
  },
  "recommended_primary_source": null,
  "notes": []
}
